<?xml version="1.0" encoding="utf-8" ?>
<dwsync>
<file name="img-1.svg" server="vps798.pairvps.com//usr/home/working/public_html/talkingheadstudio.com/" local="134080612319478781" remote="134080686600000000" Dst="1" />
<file name="img-2.svg" server="vps798.pairvps.com//usr/home/working/public_html/talkingheadstudio.com/" local="134080612319557547" remote="134080686600000000" Dst="1" />
<file name="img-3.svg" server="vps798.pairvps.com//usr/home/working/public_html/talkingheadstudio.com/" local="134080612319865108" remote="134080686600000000" Dst="1" />
<file name="img-4.svg" server="vps798.pairvps.com//usr/home/working/public_html/talkingheadstudio.com/" local="134080612320250840" remote="134080686600000000" Dst="1" />
<file name="img-5.svg" server="vps798.pairvps.com//usr/home/working/public_html/talkingheadstudio.com/" local="134080612319718002" remote="134080686600000000" Dst="1" />
<file name="img-6.svg" server="vps798.pairvps.com//usr/home/working/public_html/talkingheadstudio.com/" local="134080612319597587" remote="134080686600000000" Dst="1" />
<file name="item-1.png" server="vps798.pairvps.com//usr/home/working/public_html/talkingheadstudio.com/" local="134080612319361815" remote="134080686600000000" Dst="1" />
<file name="item-1.svg" server="vps798.pairvps.com//usr/home/working/public_html/talkingheadstudio.com/" local="134080612320011143" remote="134080686600000000" Dst="1" />
<file name="item-2.png" server="vps798.pairvps.com//usr/home/working/public_html/talkingheadstudio.com/" local="134080612319768863" remote="134080686600000000" Dst="1" />
<file name="item-2.svg" server="vps798.pairvps.com//usr/home/working/public_html/talkingheadstudio.com/" local="134080612319633377" remote="134080686600000000" Dst="1" />
<file name="item-3.png" server="vps798.pairvps.com//usr/home/working/public_html/talkingheadstudio.com/" local="134080612319678929" remote="134080686600000000" Dst="1" />
<file name="item-3.svg" server="vps798.pairvps.com//usr/home/working/public_html/talkingheadstudio.com/" local="134080612319518926" remote="134080686600000000" Dst="1" />
<file name="item-4.png" server="vps798.pairvps.com//usr/home/working/public_html/talkingheadstudio.com/" local="134080612320305253" remote="134080686600000000" Dst="1" />
<file name="item-4.svg" server="vps798.pairvps.com//usr/home/working/public_html/talkingheadstudio.com/" local="134080612319809017" remote="134080686600000000" Dst="1" />
<file name="item-5.png" server="vps798.pairvps.com//usr/home/working/public_html/talkingheadstudio.com/" local="134080612319441242" remote="134080686600000000" Dst="1" />
<file name="item-5.svg" server="vps798.pairvps.com//usr/home/working/public_html/talkingheadstudio.com/" local="134080612319908872" remote="134080686600000000" Dst="1" />
<file name="item-6.png" server="vps798.pairvps.com//usr/home/working/public_html/talkingheadstudio.com/" local="134080612320350682" remote="134080686600000000" Dst="1" />
<file name="item-6.svg" server="vps798.pairvps.com//usr/home/working/public_html/talkingheadstudio.com/" local="134080612319958233" remote="134080686600000000" Dst="1" />
<file name="item-7.png" server="vps798.pairvps.com//usr/home/working/public_html/talkingheadstudio.com/" local="134080612320197209" remote="134080686600000000" Dst="1" />
<file name="item-7.svg" server="vps798.pairvps.com//usr/home/working/public_html/talkingheadstudio.com/" local="134080612320142066" remote="134080686600000000" Dst="1" />
<file name="item-8.png" server="vps798.pairvps.com//usr/home/working/public_html/talkingheadstudio.com/" local="134080612319407032" remote="134080686600000000" Dst="1" />
<file name="item-8.svg" server="vps798.pairvps.com//usr/home/working/public_html/talkingheadstudio.com/" local="134080612320080080" remote="134080686600000000" Dst="1" />
</dwsync>